file_automation/__init__.py
file_automation/config.py
file_automation/main.py
file_automation-0.1.2.dist-info/LICENSE
file_automation-0.1.2.dist-info/METADATA
file_automation-0.1.2.dist-info/WHEEL
file_automation-0.1.2.dist-info/entry_points.txt
file_automation-0.1.2.dist-info/RECORD
