Metadata-Version: 2.1
Name: file-automation
Version: 0.1.2
Summary: File Automation - run templated shell commands for each file matched by pattern.
Author: Alexander Gorokhov
Author-email: sashgorokhov@gmail.com
Requires-Python: >=3.8
Classifier: Development Status :: 4 - Beta
Classifier: Environment :: Console
Classifier: Intended Audience :: End Users/Desktop
Classifier: Programming Language :: Python :: 3
Classifier: Programming Language :: Python :: 3.8
Classifier: Programming Language :: Python :: 3.9
Classifier: Programming Language :: Python :: 3.10
Classifier: Programming Language :: Python :: 3.11
Classifier: Programming Language :: Python :: 3.12
Classifier: Programming Language :: Python :: 3.13
Classifier: Topic :: System :: Filesystems
Classifier: Topic :: Utilities
Requires-Dist: pydantic (>=2.9.2,<3.0.0)
Requires-Dist: pyyaml (>=6.0.2,<7.0.0)
